app.py
file_splitter/__init__.py
file_splitter/app.py
file_splitter/resources/__init__.py
file_splitter/resources/filesplitter.py
file_splitter/resources/splitter.py
resources/__init__.py
resources/filesplitter.py
resources/splitter.py
FileSplitter-2.0.dist-info/LICENSE
FileSplitter-2.0.dist-info/METADATA
FileSplitter-2.0.dist-info/WHEEL
FileSplitter-2.0.dist-info/entry_points.txt
FileSplitter-2.0.dist-info/top_level.txt
FileSplitter-2.0.dist-info/RECORD
