Metadata-Version: 2.1
Name: FileSplitter
Version: 2.0
Summary: File splitter is a tool that split large file into multiple small file
Home-page: https://github.com/asrmarco13/the-file-splitter
Author: Marco Orfei
Author-email: marcoasrorfei@gmail.com
License: UNKNOWN
Project-URL: Bug tracker, https://github.com/asrmarco13/the-file-splitter/issues
Project-URL: Documentation, https://github.com/asrmarco13/the-file-splitter/blob/master/README.md
Project-URL: Source code, https://github.com/asrmarco13/the-file-splitter
Keywords: file splitter fs
Platform: UNKNOWN
Classifier: Programming Language :: Python :: 3
Classifier: License :: OSI Approved :: GNU General Public License v3 (GPLv3)
Classifier: Operating System :: OS Independent
Requires-Python: >=3.6
